LICENSE
README.md
setup.py
unless/__init__.py
unless/result.py
unless_handler.egg-info/PKG-INFO
unless_handler.egg-info/SOURCES.txt
unless_handler.egg-info/dependency_links.txt
unless_handler.egg-info/top_level.txt