Metadata-Version: 2.1
Name: unless-handler
Version: 0.2
Summary: Lightweight python library for error handling
Home-page: https://github.com/Itz-fork/Unless
Download-URL: https://github.com/Itz-fork/Unless/archive/refs/tags/v0.2.tar.gz
Author: Itz-fork
Author-email: git.itzfork@gmail.com
License: MIT
Keywords: unless,error-handler,simplified,error,python-error-handler
Classifier: Development Status :: 5 - Production/Stable
Classifier: Intended Audience :: Developers
Classifier: Topic :: Software Development :: Libraries
Classifier: License :: OSI Approved :: MIT License
Classifier: Programming Language :: Python :: 3.6
Classifier: Programming Language :: Python :: 3.7
Classifier: Programming Language :: Python :: 3.8
Classifier: Programming Language :: Python :: 3.9
Classifier: Programming Language :: Python :: 3.10
Classifier: Programming Language :: Python :: 3.11
Requires-Python: >=3.6
License-File: LICENSE
